kaeruprofiler.py
kaeruprofiler-0.0.6.dist-info/DESCRIPTION.rst
kaeruprofiler-0.0.6.dist-info/METADATA
kaeruprofiler-0.0.6.dist-info/RECORD
kaeruprofiler-0.0.6.dist-info/WHEEL
kaeruprofiler-0.0.6.dist-info/metadata.json
kaeruprofiler-0.0.6.dist-info/top_level.txt
