Metadata-Version: 2.0
Name: kaeruprofiler
Version: 0.0.6
Summary: Profiling with Key
Home-page: https://github.com/harukaeru/Kaeruprofiler
Author: harukaeru
Author-email: nekoneko.myaomyao@gmail.com
License: MIT
Platform: UNKNOWN
